Metadata-Version: 2.1
Name: epic-example
Version: 0.1
Summary: The EPIC package manager
Home-page: 
Author: Toby Killen
Author-email: support@tobykillen.com
License: MIT
